rLKK/__init__.py
rlkk-5.0.0.dist-info/METADATA
rlkk-5.0.0.dist-info/WHEEL
rlkk-5.0.0.dist-info/licenses/LICENSE
rlkk-5.0.0.dist-info/RECORD
