Metadata-Version: 2.3
Name: rLKK
Version: 5.0.0
Summary: Regularized Linear Kramers-Kronig
Project-URL: Homepage, https://github.com/kallelay/rlkk
Project-URL: Issues, https://github.com/kallelay/rlkk/issues
Author-email: Ahmed Yahia Kallel <kallelay@gmail.com>
License-File: LICENSE
Classifier: License :: OSI Approved :: MIT License
Classifier: Operating System :: OS Independent
Classifier: Programming Language :: Python :: 3
Requires-Python: >=3.7
